CHANGES.rst
LICENSE
MANIFEST.in
README.md
manage.py
setup.py
testapps/__init__.py
testapps/admin.py
testapps/models.py
testapps/tests.py
testapps/urls.py
testapps/views.py
testproject/__init__.py
testproject/settings.py
testproject/urls.py
testproject/wsgi.py
tocka_django_unslashed.egg-info/PKG-INFO
tocka_django_unslashed.egg-info/SOURCES.txt
tocka_django_unslashed.egg-info/dependency_links.txt
tocka_django_unslashed.egg-info/not-zip-safe
tocka_django_unslashed.egg-info/requires.txt
tocka_django_unslashed.egg-info/top_level.txt
unslashed/__init__.py
unslashed/apps.py
unslashed/middleware.py
unslashed/tests.py